helpscout/__init__.py
helpscout/client.py
helpscout/exceptions.py
helpscout/model.py
helpscout/prueba.py
python_helpscout_v2-1.0.1.dist-info/LICENSE.md
python_helpscout_v2-1.0.1.dist-info/METADATA
python_helpscout_v2-1.0.1.dist-info/WHEEL
python_helpscout_v2-1.0.1.dist-info/top_level.txt
python_helpscout_v2-1.0.1.dist-info/RECORD
