Metadata-Version: 2.1
Name: python-helpscout-v2
Version: 1.0.1
Summary: Wrapper to query Help Scout v2 API
Home-page: https://github.com/santiher/python-helpscout-v2
Author: santiher
License: MIT
Platform: UNKNOWN
Classifier: License :: OSI Approved :: MIT License
Classifier: Programming Language :: Python
Classifier: Programming Language :: Python :: 2
Classifier: Programming Language :: Python :: 3
Requires-Dist: requests
